openimis_be_opensearch_reports-1.3.0.dist-info/licenses/LICENSE
openimis_be_opensearch_reports-1.3.0.dist-info/licenses/LICENSE.md
opensearch_reports/__init__.py
opensearch_reports/admin.py
opensearch_reports/apps.py
opensearch_reports/gql_mutations.py
opensearch_reports/gql_queries.py
opensearch_reports/models.py
opensearch_reports/schema.py
opensearch_reports/service.py
opensearch_reports/tasks.py
opensearch_reports/urls.py
opensearch_reports/validations.py
opensearch_reports/views.py
opensearch_reports/management/__init__.py
opensearch_reports/management/commands/__init__.py
opensearch_reports/management/commands/upload_opensearch_dashboards.py
opensearch_reports/migrations/0001_initial.py
opensearch_reports/migrations/0002_default_dashboards.py
opensearch_reports/migrations/0003_individuals_groups_dashboards.py
opensearch_reports/migrations/0004_alter_historicalopensearchdashboard_date_created_and_more.py
opensearch_reports/migrations/0005_add_opensearch_rights.py
opensearch_reports/migrations/0006_add_data_update_dashboard.py
opensearch_reports/migrations/0007_historicalopensearchdashboard_synch_disabled_and_more.py
opensearch_reports/migrations/__init__.py
opensearch_reports/tests/__init__.py
opensearch_reports/tests/test_service.py
openimis_be_opensearch_reports-1.3.0.dist-info/METADATA
openimis_be_opensearch_reports-1.3.0.dist-info/WHEEL
openimis_be_opensearch_reports-1.3.0.dist-info/top_level.txt
openimis_be_opensearch_reports-1.3.0.dist-info/RECORD
