Metadata-Version: 2.4
Name: openimis-be-opensearch_reports
Version: 1.3.0
Summary: The openIMIS Backend opensearch_reports reference module.
Home-page: https://openimis.org/
Author: sniedzielski
Author-email: sniedzielski@soldevelo.com
License: GNU AGPL v3
Classifier: Environment :: Web Environment
Classifier: Framework :: Django
Classifier: Framework :: Django :: 3.0
Classifier: Intended Audience :: Developers
Classifier: License :: OSI Approved :: GNU Affero General Public License v3
Classifier: Operating System :: OS Independent
Classifier: Programming Language :: Python
Classifier: Programming Language :: Python :: 3.8
License-File: LICENSE
License-File: LICENSE.md
Requires-Dist: django
Requires-Dist: django-db-signals
Requires-Dist: djangorestframework
Requires-Dist: openimis-be-core
Dynamic: author
Dynamic: author-email
Dynamic: classifier
Dynamic: description
Dynamic: description-content-type
Dynamic: home-page
Dynamic: license
Dynamic: license-file
Dynamic: requires-dist
Dynamic: summary
